MANIFEST.in
README.rst
setup.cfg
setup.py
bin/tat_morphan_lookup
bin/tat_morphan_process_folder
bin/tat_morphan_process_text
bin/tat_morphan_stats_of_folder
py_tat_morphan/__init__.py
py_tat_morphan/constants.py
py_tat_morphan/morphan.py
py_tat_morphan/recollect_dict.py
py_tat_morphan/shared.py
py_tat_morphan/transducer.py
py_tat_morphan.egg-info/PKG-INFO
py_tat_morphan.egg-info/SOURCES.txt
py_tat_morphan.egg-info/dependency_links.txt
py_tat_morphan.egg-info/not-zip-safe
py_tat_morphan.egg-info/requires.txt
py_tat_morphan.egg-info/top_level.txt
py_tat_morphan/files/disam_rules.json
py_tat_morphan/files/error.csv
py_tat_morphan/files/exceptions.txt
py_tat_morphan/files/tatar_last.hfstol
py_tat_morphan/files/words.csv