Metadata-Version: 1.0
Name: py-tat-morphan
Version: 1.2.10
Summary: Morphological Analyser for Tatar language
Home-page: https://bitbucket.org/yaugear/py_tat_morphan/
Author: Yaugear
Author-email: ramil.gata@gmail.com
License: MIT
Keywords: morpological analyser,nlp,Tatar language
Platform: UNKNOWN
